setup.cfg
setup.py
DogPush.egg-info/PKG-INFO
DogPush.egg-info/SOURCES.txt
DogPush.egg-info/dependency_links.txt
DogPush.egg-info/requires.txt
DogPush.egg-info/top_level.txt
dogpush/__init__.py
dogpush/bcolors.py
dogpush/dogpush.py
scripts/dogpush