Metadata-Version: 1.0
Name: DogPush
Version: 0.3.4
Summary: DogPush: manage datadog alerts in local files.
Home-page: https://github.com/trueaccord/DogPush
Author: Nadav S Samet
Author-email: thesamet@gmail.com
License: Apache 2.0
Platform: UNKNOWN
